axol/py.typed
axol/user_config.py
axol/core/__main__.py
axol/core/common.py
axol/core/config.py
axol/core/search.py
axol/core/storage.py
axol/core/utils.py
axol/modules/hackernews/common.py
axol/modules/hackernews/model.py
axol/modules/hackernews/search.py
axol/modules/pinboard/model.py
axol/modules/pinboard/search.py
axol/modules/reddit/model.py
axol/modules/reddit/search.py
axol-0.1.0.dist-info/LICENSE
axol-0.1.0.dist-info/METADATA
axol-0.1.0.dist-info/WHEEL
axol-0.1.0.dist-info/top_level.txt
axol-0.1.0.dist-info/RECORD
