Metadata-Version: 2.1
Name: axol
Version: 0.1.0
Summary: Your personal search alerts
Author-email: "Dima Gerasimov (@karlicoss)" <karlicoss@gmail.com>
Maintainer-email: "Dima Gerasimov (@karlicoss)" <karlicoss@gmail.com>
License: MIT License
Project-URL: Homepage, https://github.com/karlicoss/axol
License-File: LICENSE
Requires-Dist: click
Requires-Dist: loguru
Requires-Dist: orjson
Requires-Dist: sqlalchemy
Provides-Extra: optional
Requires-Dist: python-hn ; extra == 'optional'
Requires-Dist: praw ; extra == 'optional'
Provides-Extra: testing
Requires-Dist: pytest ; extra == 'testing'
Requires-Dist: ruff ; extra == 'testing'
Requires-Dist: mypy ; extra == 'testing'
Requires-Dist: lxml ; extra == 'testing'
